{
  "response_status": { "status": 1 },
  "hotel_item": [
    {
      "hotel_code": "FRPAR",
      "hotel_name": "Appart\\342\\200\\231City Confort Paris Grande Biblioth\\303\\250que",
      "hotel_category": 4,
      "address": {
        "street_address": "70 Avenue de France - 13th district - Paris - France",
        "city_name": "Paris",
        "zip_code": "75013",
        "country_name": "France"
      },
      "city_code": "FRPAR",
      "latitude": 2.379615,
      "longitude": 2.379615,
      "min_price": 135.74,
      "currency_code": "EUR",
      "breakfast": true
    },
    {
      "hotel_code": "FRIVS",
      "hotel_name": "The Originals Residence, Le Monde Paris Ivry Confluence",
      "hotel_category": 3,
      "address": {
        "street_address": "5 all\\303\\251e Jacques Lalo\\303\\253",
        "city_name": "Ivry-sur-Seine",
        "zip_code": "94205",
        "country_name": "France"
      },
      "city_code": "FRIVS",
      "latitude": 2.40553,
      "longitude": 2.40553,
      "min_price": 89.13,
      "currency_code": "EUR",
      "breakfast": true
    },

    {
      "hotel_code": "FRIVS",
      "hotel_name": "Aparthotel Adagio Access Paris Quai d\\'Ivry",
      "hotel_category": 3,
      "address": {
        "street_address": "BLVD. DE BRANDEBOURG, 50",
        "city_name": "Ivry-sur-Seine",
        "zip_code": "94200",
        "country_name": "France"
      },
      "city_code": "FRIVS",
      "latitude": 2.3968596,
      "longitude": 2.3968596,
      "min_price": 90.08,
      "currency_code": "EUR",
      "breakfast": true
    },

    {
      "hotel_code": "FRPAR",
      "hotel_name": "Best Western Allegro Nation",
      "hotel_category": 4,
      "address": {
        "street_address": "33 Avenue du Docteur Arnold Netter - 12th district - Paris - France",
        "city_name": "Paris",
        "zip_code": "75012",
        "country_name": "France"
      },
      "city_code": "FRPAR",
      "latitude": 2.405103,
      "longitude": 2.405103,
      "min_price": 138.8,
      "currency_code": "EUR",
      "breakfast": true
    },

    {
      "hotel_code": "FRPAR",
      "hotel_name": "Citadines Place d\\'Italie Paris",
      "hotel_category": 3,
      "address": {
        "street_address": "18, place d\\'italie",
        "city_name": "Paris",
        "zip_code": "75013",
        "country_name": "France"
      },
      "city_code": "FRPAR",
      "latitude": 2.3549898,
      "longitude": 2.3549898,
      "min_price": 142.88,
      "currency_code": "EUR",
      "breakfast": true
    },

    {
      "hotel_code": "FRPAR",
      "hotel_name": "Paris Bastille",
      "hotel_category": 3,
      "address": {
        "street_address": "67 rue de lyon",
        "city_name": "Paris",
        "zip_code": "75012",
        "country_name": "France"
      },
      "city_code": "FRPAR",
      "latitude": 2.3699,
      "longitude": 2.3699,
      "min_price": 149.48,
      "currency_code": "EUR",
      "breakfast": true
    },

    {
      "hotel_code": "FRPAR",
      "hotel_name": "Quality Hotel & Suites Bercy Biblioth\\303\\250que by HappyCulture",
      "hotel_category": 3,
      "address": {
        "street_address": "15 rue de tolbiac",
        "city_name": "Paris",
        "zip_code": "75013",
        "country_name": "France"
      },
      "city_code": "FRPAR",
      "latitude": 2.374866,
      "longitude": 2.374866,
      "min_price": 114.88,
      "currency_code": "EUR"
    },

    {
      "hotel_code": "FRPAR",
      "hotel_name": "Residhome Paris Gare de Lyon - Jacqueline de Romilly",
      "hotel_category": 3,
      "address": {
        "street_address": "47 Rue Jorge Sempr\\303\\271n",
        "city_name": "Paris",
        "zip_code": "75012",
        "country_name": "France"
      },
      "city_code": "FRPAR",
      "latitude": 2.384078,
      "longitude": 2.384078,
      "min_price": 128.88,
      "currency_code": "EUR",
      "breakfast": true
    },

    {
      "hotel_code": "FRPAR",
      "hotel_name": "Coypel by Magna Arbor ",
      "hotel_category": 3,
      "address": {
        "street_address": "Rue Coypel, 2",
        "city_name": "Paris",
        "zip_code": "75013",
        "country_name": "France"
      },
      "city_code": "FRPAR",
      "latitude": 2.356644,
      "longitude": 2.356644,
      "min_price": 137.52,
      "currency_code": "EUR"
    },

    {
      "hotel_code": "FRPAR",
      "hotel_name": "H\\303\\264tel du Jardin des Plantes",
      "hotel_category": 3,
      "address": {
        "street_address": "5, rue linne",
        "city_name": "Paris",
        "zip_code": "75005",
        "country_name": "France"
      },
      "city_code": "FRPAR",
      "latitude": 2.354711,
      "longitude": 2.354711,
      "min_price": 156.1,
      "currency_code": "EUR"
    },

    {
      "hotel_code": "FRPAR",
      "hotel_name": "Kyriad Hotel XIII Italie Gobelins",
      "hotel_category": 3,
      "address": {
        "street_address": "5 rue veronese",
        "city_name": "Paris",
        "zip_code": "75013",
        "country_name": "France"
      },
      "city_code": "FRPAR",
      "latitude": 2.3551,
      "longitude": 2.3551,
      "min_price": 154.19,
      "currency_code": "EUR"
    },

    {
      "hotel_code": "FRPAR",
      "hotel_name": "Istria by Magna Arbor ",
      "hotel_category": 3,
      "address": {
        "street_address": "RUE CAMPAGNE PREMIERE, 29",
        "city_name": "Paris",
        "zip_code": "75014",
        "country_name": "France"
      },
      "city_code": "FRPAR",
      "latitude": 2.331641,
      "longitude": 2.331641,
      "min_price": 140.35,
      "currency_code": "EUR",
      "breakfast": true
    },

    {
      "hotel_code": "FRPAR",
      "hotel_name": "Agate H\\303\\264tel",
      "hotel_category": 3,
      "address": {
        "street_address": "COURS DE VINCENNES, 8",
        "city_name": "Paris",
        "zip_code": "75012",
        "country_name": "France"
      },
      "city_code": "FRPAR",
      "latitude": 2.3996971,
      "longitude": 2.3996971,
      "min_price": 113.78,
      "currency_code": "EUR",
      "breakfast": true
    },

    {
      "hotel_code": "FRGTY",
      "hotel_name": "ibis Paris Porte d\\'Italie",
      "hotel_category": 3,
      "address": {
        "street_address": "13 Rue Du Val De Marne",
        "city_name": "Gentilly",
        "zip_code": "94250",
        "country_name": "France"
      },
      "city_code": "FRGTY",
      "latitude": 2.35121,
      "longitude": 2.35121,
      "min_price": 142.33,
      "currency_code": "EUR",
      "breakfast": true
    },

    {
      "hotel_code": "FRIVS",
      "hotel_name": "Break & Home Paris Italie Porte de Choisy",
      "hotel_category": 3,
      "address": {
        "street_address": "23 Avenue de Verdun",
        "city_name": "Ivry-sur-Seine",
        "zip_code": "94200",
        "country_name": "France"
      },
      "city_code": "FRIVS",
      "latitude": 2.36825,
      "longitude": 2.36825,
      "min_price": 84.88,
      "currency_code": "EUR",
      "breakfast": true
    },

    {
      "hotel_code": "FRMTG",
      "hotel_name": "ibis Paris Porte D\\'Orleans",
      "hotel_category": 3,
      "address": {
        "street_address": "33 rue barbes paris",
        "city_name": "Montrouge",
        "zip_code": "92120",
        "country_name": "France"
      },
      "city_code": "FRMTG",
      "latitude": 2.3709845,
      "longitude": 2.3709845,
      "min_price": 142.98,
      "currency_code": "EUR",
      "breakfast": true
    },

    {
      "hotel_code": "FRPAR",
      "hotel_name": "Citadines Bastille Marais Paris",
      "hotel_category": 3,
      "address": {
        "street_address": "boulevard richard lenoir, 37",
        "city_name": "Paris",
        "zip_code": "75011",
        "country_name": "France"
      },
      "city_code": "FRPAR",
      "latitude": 2.37089,
      "longitude": 2.37089,
      "min_price": 151.88,
      "currency_code": "EUR",
      "breakfast": true
    },

    {
      "hotel_code": "FRLKB",
      "hotel_name": "Campanile Paris Porte d\\'Italie - Le Kremlin Bic\\303\\252tre",
      "hotel_category": 3,
      "address": {
        "street_address": "boulevard du general de gaulle",
        "city_name": "Le Kremlin-Bicetre",
        "zip_code": "94270",
        "country_name": "France"
      },
      "city_code": "FRLKB",
      "latitude": 2.3603,
      "longitude": 2.3603,
      "min_price": 67.98,
      "currency_code": "EUR",
      "breakfast": true
    },

    {
      "hotel_code": "FRPAR",
      "hotel_name": "H\\303\\264tel L\\'Interlude",
      "hotel_category": 3,
      "address": {
        "street_address": "AVENUE DAUMESNIL 258",
        "city_name": "Paris",
        "zip_code": "75012",
        "country_name": "France"
      },
      "city_code": "FRPAR",
      "latitude": 2.403795,
      "longitude": 2.403795,
      "min_price": 144.7,
      "currency_code": "EUR"
    },

    {
      "hotel_code": "FRIVS",
      "hotel_name": "Comfort Hotel Paris Porte d\\'Ivry",
      "hotel_category": 3,
      "address": {
        "street_address": "1 A 11, RUE RENE VILLARS",
        "city_name": "Ivry-sur-Seine",
        "zip_code": "94200",
        "country_name": "France"
      },
      "city_code": "FRIVS",
      "latitude": 2.376128,
      "longitude": 2.376128,
      "min_price": 86.48,
      "currency_code": "EUR",
      "breakfast": true
    },

    {
      "hotel_code": "FRPAR",
      "hotel_name": "Pink Hotel",
      "hotel_category": 3,
      "address": {
        "street_address": "RUE DUGOMMIER 20 BIS",
        "city_name": "Paris",
        "zip_code": "75012",
        "country_name": "France"
      },
      "city_code": "FRPAR",
      "latitude": 2.391788,
      "longitude": 2.391788,
      "min_price": 159.13,
      "currency_code": "EUR"
    },

    {
      "hotel_code": "FRIVS",
      "hotel_name": "Apogia Paris",
      "hotel_category": 3,
      "address": {
        "street_address": "14 Boulevard Paul Vaillant-Couturier",
        "city_name": "Ivry-sur-Seine",
        "zip_code": "94200",
        "country_name": "France"
      },
      "city_code": "FRIVS",
      "latitude": 2.395231,
      "longitude": 2.395231,
      "min_price": 134.01,
      "currency_code": "EUR",
      "breakfast": true
    },

    {
      "hotel_code": "FRCNP",
      "hotel_name": "Novotel Paris Sud Porte de Charenton",
      "hotel_category": 4,
      "address": {
        "street_address": "3-5 Place Des Marseillais",
        "city_name": "Charenton-le-Pont",
        "zip_code": "94227",
        "country_name": "France"
      },
      "city_code": "FRCNP",
      "latitude": 2.405139,
      "longitude": 2.405139,
      "min_price": 154.88,
      "currency_code": "EUR",
      "breakfast": true
    },

    {
      "hotel_code": "FRPAR",
      "hotel_name": "Hotel Inn Design Paris Place d\\'Italie",
      "hotel_category": 3,
      "address": {
        "street_address": "178 boulevard vincent auriol",
        "city_name": "Paris",
        "zip_code": "75013",
        "country_name": "France"
      },
      "city_code": "FRPAR",
      "latitude": 2.357355,
      "longitude": 2.357355,
      "min_price": 157.84,
      "currency_code": "EUR"
    }
  ]
}
